odoo/addons/project_custom_info/README.rst
odoo/addons/project_custom_info/__init__.py
odoo/addons/project_custom_info/__manifest__.py
odoo/addons/project_custom_info/demo/custom.info.category.csv
odoo/addons/project_custom_info/demo/custom.info.property.csv
odoo/addons/project_custom_info/demo/custom.info.template.csv
odoo/addons/project_custom_info/demo/project_project.xml
odoo/addons/project_custom_info/i18n/es.po
odoo/addons/project_custom_info/i18n/it.po
odoo/addons/project_custom_info/i18n/project_custom_info.pot
odoo/addons/project_custom_info/models/__init__.py
odoo/addons/project_custom_info/models/project_project.py
odoo/addons/project_custom_info/readme/CONTRIBUTORS.rst
odoo/addons/project_custom_info/readme/DESCRIPTION.rst
odoo/addons/project_custom_info/readme/USAGE.rst
odoo/addons/project_custom_info/static/description/icon.png
odoo/addons/project_custom_info/static/description/index.html
odoo/addons/project_custom_info/views/project_project_view.xml
odoo13_addon_project_custom_info-13.0.1.0.1.dev7.dist-info/METADATA
odoo13_addon_project_custom_info-13.0.1.0.1.dev7.dist-info/WHEEL
odoo13_addon_project_custom_info-13.0.1.0.1.dev7.dist-info/top_level.txt
odoo13_addon_project_custom_info-13.0.1.0.1.dev7.dist-info/RECORD
